{
	"description": "项目配置文件。",
	"setting": {
		"urlCheck": false,
		"es6": true,
		"postcss": true,
		"minified": true,
		"newFeature": true
	},
	"compileType": "miniprogram",
	"libVersion": "1.9.90",
	"appid": "wx75befcb556e56774",
	"projectname": "quick",
	"condition": {
		"search": {
			"current": -1,
			"list": []
		},
		"conversation": {
			"current": -1,
			"list": []
		},
		"plugin": {
			"current": -1,
			"list": []
		},
		"game": {
			"current": -1,
			"list": []
		},
		"miniprogram": {
			"current": -1,
			"list": [
				{
					"id": -1,
					"name": "qrcode",
					"pathName": "pages/qrcode/qrcode",
					"query": "id=11",
					"scene": "1007"
				},
				{
					"id": -1,
					"name": "apply",
					"pathName": "pages/apply/apply",
					"query": "",
					"scene": "1007"
				},
				{
					"id": 2,
					"name": "登录",
					"pathName": "component/platLogin/platLogin",
					"query": "uuid=54654565465151651rgfsfdgf",
					"scene": "1011"
				},
				{
					"id": 3,
					"name": "楼兰转账",
					"pathName": "component/loulanpay/loulanpay",
					"query": "orderNo=lqldez6biv1fque5hlxgxijj5grqfbez",
					"scene": "1011"
				}
			]
		}
	}
}